DiscreteLatticeMech/__init__.py
DiscreteLatticeMech/Core/AsymptSystemSol.py
DiscreteLatticeMech/Core/AsymptoticForcesMoments.py
DiscreteLatticeMech/Core/EffectiveProperties.py
DiscreteLatticeMech/Core/ReadInput.py
DiscreteLatticeMech/Core/Solver.py
DiscreteLatticeMech/Core/StiffFlexibilTensors.py
DiscreteLatticeMech/Core/StressVector.py
DiscreteLatticeMech/Core/WriteFiles.py
DiscreteLatticeMech/Core/__init__.py
DiscreteLatticeMech/GUI/GUI_discrete_lattice.py
DiscreteLatticeMech/GUI/icone_moins.bmp
DiscreteLatticeMech/GUI/icone_moins_point.bmp
DiscreteLatticeMech/GUI/icone_moins_poutre.bmp
DiscreteLatticeMech/GUI/icone_plus_point.bmp
DiscreteLatticeMech/GUI/icone_plus_poutre.bmp
DiscreteLatticeMech/SampleInputs/InputData_CarreReentrantEx.json
DiscreteLatticeMech/SampleInputs/InputData_Diamond45Ex.json
DiscreteLatticeMech/SampleInputs/InputData_HexachiralEx.json
DiscreteLatticeMech/SampleInputs/InputData_HoneycombEx.json
DiscreteLatticeMech/SampleInputs/InputData_KagomeEx.json
DiscreteLatticeMech/SampleInputs/InputData_SquareEx.json
DiscreteLatticeMech/SampleInputs/InputData_TriangleEx.json
DiscreteLatticeMech-1.0.0.dist-info/LICENSE
DiscreteLatticeMech-1.0.0.dist-info/METADATA
DiscreteLatticeMech-1.0.0.dist-info/WHEEL
DiscreteLatticeMech-1.0.0.dist-info/top_level.txt
DiscreteLatticeMech-1.0.0.dist-info/RECORD
