Metadata-Version: 2.1
Name: DiscreteLatticeMech
Version: 1.0.0
Summary: DiscreteLatticeMech
Home-page: https://github.com/nkarathan/DiscreteLatticeMech
Author: Nikos Karathanasopoulos
Author-email: karathanasopoulosn@gmail.com
License: MIT
Platform: UNKNOWN
Classifier: Programming Language :: Python :: 3
Classifier: License :: OSI Approved
Classifier: Operating System :: OS Independent
Requires-Dist: numpy
Requires-Dist: jsonschema
Requires-Dist: matplotlib
Requires-Dist: pytest
